timecli/commands/__init__.py
timecli/commands/oracle.py
timecli/commands/pomodoro.py
timecli/core/utils.py
timecli/main.py
timecli-0.3.2.dist-info/entry_points.txt
timecli-0.3.2.dist-info/WHEEL
timecli-0.3.2.dist-info/METADATA
timecli-0.3.2.dist-info/RECORD
