Metadata-Version: 2.1
Name: timecli
Version: 0.3.2
Summary: 
Keywords: timecli,oracle
Author: gelleson
Author-email: go.gelleson@gmail.com
Requires-Python: >=3.7,<4.0
Classifier: Programming Language :: Python :: 3
Classifier: Programming Language :: Python :: 3.10
Classifier: Programming Language :: Python :: 3.7
Classifier: Programming Language :: Python :: 3.8
Classifier: Programming Language :: Python :: 3.9
Requires-Dist: toml (>=0.10.2,<0.11.0)
Requires-Dist: typer[all] (>=0.4.1,<0.5.0)
